README.rst
setup.py
scalehub/__init__.py
scalehub/hub.py
scalehub/status.py
scalehub/worker.py
scalehub.egg-info/PKG-INFO
scalehub.egg-info/SOURCES.txt
scalehub.egg-info/dependency_links.txt
scalehub.egg-info/requires.txt
scalehub.egg-info/top_level.txt