Metadata-Version: 1.1
Name: scalehub
Version: 1.0.0b1
Summary: Test automation framework
Home-page: https://github.com/scalehub/scalehub
Author: PyScale team
Author-email: wedonthaveemailyet@pyscale.com
License: MIT
Keywords: testing automation
Platform: UNKNOWN
Classifier: Development Status :: 3 - Alpha
Classifier: Intended Audience :: Developers
Classifier: Topic :: Software Development :: Testing
Classifier: License :: OSI Approved :: MIT License
Classifier: Programming Language :: Python :: 2.7
